mcp_os/__init__.py
mcp_os/converters/__init__.py
mcp_os/core/__init__.py
mcp_os/core/complete.py
mcp_os-0.1.0.dist-info/METADATA
mcp_os-0.1.0.dist-info/WHEEL
mcp_os-0.1.0.dist-info/licenses/LICENSE
mcp_os-0.1.0.dist-info/RECORD
