Metadata-Version: 2.4
Name: mcp-os
Version: 0.1.0
Summary: Garbage-collector style context manager for LLM prompt messages.
Author-email: Sarmad Qadri <sarmad@lastmileai.dev>
License:                                  Apache License
License-File: LICENSE
Classifier: License :: OSI Approved :: Apache Software License
Classifier: Operating System :: OS Independent
Classifier: Programming Language :: Python :: 3
Requires-Python: >=3.10
Requires-Dist: mcp>=1.10.1
Requires-Dist: pydantic>=2.11.7
Requires-Dist: tiktoken>=0.9.0
Provides-Extra: anthropic
Requires-Dist: anthropic>=0.57.1; extra == 'anthropic'
Provides-Extra: openai
Requires-Dist: openai>=1.93.3; extra == 'openai'
